{
	"credit": "Made with Blockbench",
	"texture_size": [64, 64],
	"textures": {
		"0": "metal_tools:floating_metal_axe",
		"1": "metal_tools:floating_lightning",
		"2": "metal_tools:floating_axe"
	},
	"elements": [
		{
			"from": [7.5, 6.5, 6.25],
			"to": [8.5, 9.5, 9.25],
			"rotation": {"angle": 45, "axis": "x", "origin": [8, 7.75, 8]},
			"faces": {
				"north": {"uv": [8.508, 5.758, 8.992, 7.242], "texture": "#0"},
				"east": {"uv": [7.008, 5.758, 8.492, 7.242], "texture": "#0"},
				"south": {"uv": [10.508, 5.758, 10.992, 7.242], "texture": "#0"},
				"west": {"uv": [9.008, 5.758, 10.492, 7.242], "texture": "#0"},
				"up": {"uv": [8.992, 5.742, 8.508, 4.258], "texture": "#0"},
				"down": {"uv": [9.492, 4.258, 9.008, 5.742], "texture": "#0"}
			}
		},
		{
			"from": [7.2495, 6.4995, 7.4995],
			"to": [8.7505, 8.0005, 8.5005],
			"rotation": {"angle": 0, "axis": "y", "origin": [8.25, 11.5, 8]},
			"faces": {
				"north": {"uv": [11.508, 2.258, 12.242, 2.992], "texture": "#0"},
				"east": {"uv": [11.008, 2.258, 11.492, 2.992], "texture": "#0"},
				"south": {"uv": [12.758, 2.258, 13.492, 2.992], "texture": "#0"},
				"west": {"uv": [12.258, 2.258, 12.742, 2.992], "texture": "#0"},
				"up": {"uv": [12.242, 2.242, 11.508, 1.758], "texture": "#0"},
				"down": {"uv": [12.992, 1.758, 12.258, 2.242], "texture": "#0"}
			}
		},
		{
			"from": [7, 7.5, 7.25],
			"to": [9, 8.5, 8.25],
			"rotation": {"angle": 45, "axis": "x", "origin": [8, 7.75, 8]},
			"faces": {
				"north": {"uv": [5.758, 5.008, 6.742, 5.492], "texture": "#0"},
				"east": {"uv": [5.258, 5.008, 5.742, 5.492], "texture": "#0"},
				"south": {"uv": [7.258, 5.008, 8.242, 5.492], "texture": "#0"},
				"west": {"uv": [6.758, 5.008, 7.242, 5.492], "texture": "#0"},
				"up": {"uv": [6.742, 4.992, 5.758, 4.508], "texture": "#0"},
				"down": {"uv": [7.742, 4.508, 6.758, 4.992], "texture": "#0"}
			}
		},
		{
			"from": [7, 6.25, 6.75],
			"to": [9, 6.75, 9.25],
			"rotation": {"angle": 0, "axis": "y", "origin": [8.25, 11.5, 8]},
			"faces": {
				"north": {"uv": [8.258, 10.508, 9.242, 10.742], "texture": "#0"},
				"east": {"uv": [7.008, 10.508, 8.242, 10.742], "texture": "#0"},
				"south": {"uv": [10.508, 10.508, 11.492, 10.742], "texture": "#0"},
				"west": {"uv": [9.258, 10.508, 10.492, 10.742], "texture": "#0"},
				"up": {"uv": [9.242, 10.492, 8.258, 9.258], "texture": "#0"},
				"down": {"uv": [10.242, 9.258, 9.258, 10.492], "texture": "#0"}
			}
		},
		{
			"from": [7.2495, -6.7505, 7.2495],
			"to": [8.7505, 6.2505, 8.7505],
			"rotation": {"angle": 0, "axis": "y", "origin": [8.25, 4.25, 8]},
			"faces": {
				"north": {"uv": [0.758, 5.258, 1.492, 11.742], "texture": "#0"},
				"east": {"uv": [0.008, 5.258, 0.742, 11.742], "texture": "#0"},
				"south": {"uv": [2.258, 5.258, 2.992, 11.742], "texture": "#0"},
				"west": {"uv": [1.508, 5.258, 2.242, 11.742], "texture": "#0"},
				"up": {"uv": [1.492, 5.242, 0.758, 4.508], "texture": "#0"},
				"down": {"uv": [2.242, 4.508, 1.508, 5.242], "texture": "#0"}
			}
		},
		{
			"from": [7, 5.25, 6.75],
			"to": [9, 5.75, 9.25],
			"rotation": {"angle": 0, "axis": "y", "origin": [8.25, 11.75, 8]},
			"faces": {
				"north": {"uv": [5.008, 1.258, 5.992, 1.492], "texture": "#0"},
				"east": {"uv": [3.758, 1.258, 4.992, 1.492], "texture": "#0"},
				"south": {"uv": [7.258, 1.258, 8.242, 1.492], "texture": "#0"},
				"west": {"uv": [6.008, 1.258, 7.242, 1.492], "texture": "#0"},
				"up": {"uv": [5.992, 1.242, 5.008, 0.008], "texture": "#0"},
				"down": {"uv": [6.992, 0.008, 6.008, 1.242], "texture": "#0"}
			}
		},
		{
			"from": [7, -2.25, 6.75],
			"to": [9, -1.75, 9.25],
			"rotation": {"angle": 0, "axis": "y", "origin": [8.25, 11.75, 8]},
			"faces": {
				"north": {"uv": [8.258, 8.758, 9.242, 8.992], "texture": "#0"},
				"east": {"uv": [7.008, 8.758, 8.242, 8.992], "texture": "#0"},
				"south": {"uv": [10.508, 8.758, 11.492, 8.992], "texture": "#0"},
				"west": {"uv": [9.258, 8.758, 10.492, 8.992], "texture": "#0"},
				"up": {"uv": [9.242, 8.742, 8.258, 7.508], "texture": "#0"},
				"down": {"uv": [10.242, 7.508, 9.258, 8.742], "texture": "#0"}
			}
		},
		{
			"from": [7, -1.25, 6.75],
			"to": [9, -0.75, 9.25],
			"rotation": {"angle": 0, "axis": "y", "origin": [8.25, 11.5, 8]},
			"faces": {
				"north": {"uv": [10.508, 1.258, 11.492, 1.492], "texture": "#0"},
				"east": {"uv": [9.258, 1.258, 10.492, 1.492], "texture": "#0"},
				"south": {"uv": [12.758, 1.258, 13.742, 1.492], "texture": "#0"},
				"west": {"uv": [11.508, 1.258, 12.742, 1.492], "texture": "#0"},
				"up": {"uv": [11.492, 1.242, 10.508, 0.008], "texture": "#0"},
				"down": {"uv": [12.492, 0.008, 11.508, 1.242], "texture": "#0"}
			}
		},
		{
			"from": [7, -7.75, 7],
			"to": [9, -6.75, 9],
			"rotation": {"angle": 0, "axis": "y", "origin": [8.25, 4.25, 8]},
			"faces": {
				"north": {"uv": [11.008, 4.258, 11.992, 4.742], "texture": "#0"},
				"east": {"uv": [10.008, 4.258, 10.992, 4.742], "texture": "#0"},
				"south": {"uv": [13.008, 4.258, 13.992, 4.742], "texture": "#0"},
				"west": {"uv": [12.008, 4.258, 12.992, 4.742], "texture": "#0"},
				"up": {"uv": [11.992, 4.242, 11.008, 3.258], "texture": "#0"},
				"down": {"uv": [12.992, 3.258, 12.008, 4.242], "texture": "#0"}
			}
		},
		{
			"from": [7.5, -5.47155, -1.50815],
			"to": [8.5, -3.97155, -0.00815],
			"rotation": {"angle": -45, "axis": "x", "origin": [8, 4.10355, 7.81409]},
			"faces": {
				"north": {"uv": [0.758, 0.758, 1.242, 1.492], "texture": "#0"},
				"east": {"uv": [0.008, 0.758, 0.742, 1.492], "texture": "#0"},
				"south": {"uv": [2.008, 0.758, 2.492, 1.492], "texture": "#0"},
				"west": {"uv": [1.258, 0.758, 1.992, 1.492], "texture": "#0"},
				"up": {"uv": [1.242, 0.742, 0.758, 0.008], "texture": "#0"},
				"down": {"uv": [1.742, 0.008, 1.258, 0.742], "texture": "#0"}
			}
		},
		{
			"name": "lighting",
			"from": [8, 4.75, 1.7],
			"to": [8, 11.25, 12.7],
			"rotation": {"angle": 0, "axis": "y", "origin": [8.25, 4, 8]},
			"faces": {
				"north": {"uv": [0, 0, 0, 6.5], "rotation": 180, "texture": "#1"},
				"east": {"uv": [0, 0, 6.5, 11], "rotation": 270, "texture": "#1"},
				"south": {"uv": [0, 6.5, 0, 0], "texture": "#1"},
				"west": {"uv": [6.5, 0, 0, 11], "rotation": 90, "texture": "#1"},
				"up": {"uv": [0, 0, 0, 11], "rotation": 180, "texture": "#1"},
				"down": {"uv": [0, 0, 0, 11], "texture": "#1"}
			}
		},
		{
			"from": [8, 2.10355, 0.17157],
			"to": [8, 11.10355, 3.67157],
			"rotation": {"angle": 0, "axis": "y", "origin": [8, 6.35355, 7.92157]},
			"faces": {
				"north": {"uv": [0.015, 0.015, 0.015, 4.485], "texture": "#2"},
				"east": {"uv": [0.015, 0.015, 1.735, 4.485], "texture": "#2"},
				"south": {"uv": [0.015, 0.015, 0.015, 4.485], "texture": "#2"},
				"west": {"uv": [1.765, 0.015, 3.485, 4.485], "texture": "#2"},
				"up": {"uv": [0.015, 1.735, 0.015, 0.015], "texture": "#2"},
				"down": {"uv": [0.015, 0.015, 0.015, 1.735], "texture": "#2"}
			}
		},
		{
			"from": [7.75, 8.60355, 1.67157],
			"to": [8.25, 11.10355, 7.67157],
			"rotation": {"angle": 0, "axis": "y", "origin": [8, 6.35355, 7.92157]},
			"faces": {
				"north": {"uv": [13.765, 10.015, 13.985, 11.235], "texture": "#2"},
				"east": {"uv": [0.015, 9.015, 2.985, 10.235], "texture": "#2"},
				"south": {"uv": [13.765, 11.265, 13.985, 12.485], "texture": "#2"},
				"west": {"uv": [3.015, 9.015, 5.985, 10.235], "texture": "#2"},
				"up": {"uv": [12.235, 10.485, 12.015, 7.515], "texture": "#2"},
				"down": {"uv": [12.235, 10.515, 12.015, 13.485], "texture": "#2"}
			}
		},
		{
			"from": [7.75, 4.10355, 1.67157],
			"to": [8.25, 8.60355, 3.67157],
			"rotation": {"angle": 0, "axis": "y", "origin": [8, 6.35355, 7.92157]},
			"faces": {
				"north": {"uv": [12.765, 8.765, 12.985, 10.985], "texture": "#2"},
				"east": {"uv": [10.515, 0.015, 11.485, 2.235], "texture": "#2"},
				"south": {"uv": [13.015, 8.765, 13.235, 10.985], "texture": "#2"},
				"west": {"uv": [10.515, 2.265, 11.485, 4.485], "texture": "#2"},
				"up": {"uv": [12.985, 11.985, 12.765, 11.015], "texture": "#2"},
				"down": {"uv": [14.485, 2.265, 14.265, 3.235], "texture": "#2"}
			}
		},
		{
			"from": [7.5, 6.25, 5.5],
			"to": [8.5, 10.25, 6],
			"rotation": {"angle": 45, "axis": "x", "origin": [8, 8, 8.25]},
			"faces": {
				"north": {"uv": [11.515, 2.265, 11.985, 4.235], "texture": "#2"},
				"east": {"uv": [13.265, 11.265, 13.485, 13.235], "texture": "#2"},
				"south": {"uv": [3.015, 11.515, 3.485, 13.485], "texture": "#2"},
				"west": {"uv": [11.515, 13.265, 11.735, 15.235], "texture": "#2"},
				"up": {"uv": [13.985, 14.485, 13.515, 14.265], "texture": "#2"},
				"down": {"uv": [2.235, 14.515, 1.765, 14.735], "texture": "#2"}
			}
		},
		{
			"from": [7.5, 8.35355, 3.92157],
			"to": [8.5, 8.85355, 5.42157],
			"rotation": {"angle": 0, "axis": "y", "origin": [8, 6.60355, 7.67157]},
			"faces": {
				"north": {"uv": [2.265, 14.515, 2.735, 14.735], "texture": "#2"},
				"east": {"uv": [14.265, 11.265, 14.985, 11.485], "texture": "#2"},
				"south": {"uv": [14.515, 2.265, 14.985, 2.485], "texture": "#2"},
				"west": {"uv": [14.265, 11.515, 14.985, 11.735], "texture": "#2"},
				"up": {"uv": [11.985, 8.985, 11.515, 8.265], "texture": "#2"},
				"down": {"uv": [1.485, 13.765, 1.015, 14.485], "texture": "#2"}
			}
		},
		{
			"from": [7.5, 11.03553, 7.89645],
			"to": [8.5, 11.53553, 9.39645],
			"rotation": {"angle": 0, "axis": "y", "origin": [8, 11.28553, 8.64645]},
			"faces": {
				"north": {"uv": [14.515, 2.515, 14.985, 2.735], "texture": "#2"},
				"east": {"uv": [14.265, 11.765, 14.985, 11.985], "texture": "#2"},
				"south": {"uv": [14.515, 2.765, 14.985, 2.985], "texture": "#2"},
				"west": {"uv": [14.265, 12.015, 14.985, 12.235], "texture": "#2"},
				"up": {"uv": [1.985, 14.485, 1.515, 13.765], "texture": "#2"},
				"down": {"uv": [14.235, 1.765, 13.765, 2.485], "texture": "#2"}
			}
		},
		{
			"from": [7.5, 4.85355, 3.42157],
			"to": [8.5, 8.85355, 3.92157],
			"rotation": {"angle": 0, "axis": "y", "origin": [8, 6.60355, 7.67157]},
			"faces": {
				"north": {"uv": [3.515, 11.515, 3.985, 13.485], "texture": "#2"},
				"east": {"uv": [11.765, 13.265, 11.985, 15.235], "texture": "#2"},
				"south": {"uv": [4.015, 11.515, 4.485, 13.485], "texture": "#2"},
				"west": {"uv": [12.515, 13.265, 12.735, 15.235], "texture": "#2"},
				"up": {"uv": [14.985, 3.235, 14.515, 3.015], "texture": "#2"},
				"down": {"uv": [3.985, 14.515, 3.515, 14.735], "texture": "#2"}
			}
		},
		{
			"from": [7.5, 10.375, 6.5],
			"to": [8.5, 10.875, 9],
			"rotation": {"angle": 45, "axis": "x", "origin": [8, 7.625, 7.25]},
			"faces": {
				"north": {"uv": [14.515, 3.765, 14.985, 3.985], "texture": "#2"},
				"east": {"uv": [13.765, 12.515, 14.985, 12.735], "texture": "#2"},
				"south": {"uv": [4.015, 14.515, 4.485, 14.735], "texture": "#2"},
				"west": {"uv": [13.765, 12.765, 14.985, 12.985], "texture": "#2"},
				"up": {"uv": [12.985, 13.235, 12.515, 12.015], "texture": "#2"},
				"down": {"uv": [13.235, 0.015, 12.765, 1.235], "texture": "#2"}
			}
		},
		{
			"from": [7.75, 5.43566, 9.03553],
			"to": [8.25, 9.93566, 12.53553],
			"rotation": {"angle": 0, "axis": "y", "origin": [8, 7.68566, 7.28553]},
			"faces": {
				"north": {"uv": [13.015, 11.015, 13.235, 13.235], "texture": "#2"},
				"east": {"uv": [7.015, 0.015, 8.735, 2.235], "texture": "#2"},
				"south": {"uv": [13.265, 0.015, 13.485, 2.235], "texture": "#2"},
				"west": {"uv": [7.015, 2.265, 8.735, 4.485], "texture": "#2"},
				"up": {"uv": [8.235, 15.235, 8.015, 13.515], "texture": "#2"},
				"down": {"uv": [13.735, 8.015, 13.515, 9.735], "texture": "#2"}
			}
		},
		{
			"from": [7.5, 5.18566, 10.28553],
			"to": [8.5, 8.68566, 10.78553],
			"rotation": {"angle": 0, "axis": "y", "origin": [8, 7.93566, 7.53553]},
			"faces": {
				"north": {"uv": [9.515, 11.515, 9.985, 13.235], "texture": "#2"},
				"east": {"uv": [8.265, 13.515, 8.485, 15.235], "texture": "#2"},
				"south": {"uv": [10.015, 11.515, 10.485, 13.235], "texture": "#2"},
				"west": {"uv": [8.515, 13.515, 8.735, 15.235], "texture": "#2"},
				"up": {"uv": [14.985, 4.235, 14.515, 4.015], "texture": "#2"},
				"down": {"uv": [14.985, 4.265, 14.515, 4.485], "texture": "#2"}
			}
		},
		{
			"from": [7.5, 5.18566, 10.78553],
			"to": [8.5, 5.68566, 12.78553],
			"rotation": {"angle": 0, "axis": "y", "origin": [8, 7.93566, 7.53553]},
			"faces": {
				"north": {"uv": [14.515, 4.515, 14.985, 4.735], "texture": "#2"},
				"east": {"uv": [14.265, 3.265, 15.235, 3.485], "texture": "#2"},
				"south": {"uv": [14.515, 4.765, 14.985, 4.985], "texture": "#2"},
				"west": {"uv": [14.265, 3.515, 15.235, 3.735], "texture": "#2"},
				"up": {"uv": [13.235, 14.235, 12.765, 13.265], "texture": "#2"},
				"down": {"uv": [13.735, 13.265, 13.265, 14.235], "texture": "#2"}
			}
		},
		{
			"from": [8, 2.10355, -0.32843],
			"to": [8, 11.10355, 3.17157],
			"rotation": {"angle": 0, "axis": "y", "origin": [8, 6.35355, 7.42157]},
			"faces": {
				"north": {"uv": [0.015, 0.015, 0.015, 4.485], "texture": "#2"},
				"east": {"uv": [3.515, 0.015, 5.235, 4.485], "texture": "#2"},
				"south": {"uv": [0.015, 0.015, 0.015, 4.485], "texture": "#2"},
				"west": {"uv": [0.015, 4.515, 1.735, 8.985], "texture": "#2"},
				"up": {"uv": [0.015, 1.735, 0.015, 0.015], "texture": "#2"},
				"down": {"uv": [0.015, 0.015, 0.015, 1.735], "texture": "#2"}
			}
		},
		{
			"from": [7.75, 8.60355, 1.17157],
			"to": [8.25, 11.10355, 7.17157],
			"rotation": {"angle": 0, "axis": "y", "origin": [8, 6.35355, 7.42157]},
			"faces": {
				"north": {"uv": [13.765, 13.015, 13.985, 14.235], "texture": "#2"},
				"east": {"uv": [6.015, 9.015, 8.985, 10.235], "texture": "#2"},
				"south": {"uv": [14.015, 0.015, 14.235, 1.235], "texture": "#2"},
				"west": {"uv": [9.015, 9.015, 11.985, 10.235], "texture": "#2"},
				"up": {"uv": [12.485, 10.485, 12.265, 7.515], "texture": "#2"},
				"down": {"uv": [12.485, 10.515, 12.265, 13.485], "texture": "#2"}
			}
		},
		{
			"from": [7.75, 4.10355, 1.17157],
			"to": [8.25, 8.60355, 3.17157],
			"rotation": {"angle": 0, "axis": "y", "origin": [8, 6.35355, 7.42157]},
			"faces": {
				"north": {"uv": [13.265, 2.265, 13.485, 4.485], "texture": "#2"},
				"east": {"uv": [10.515, 4.515, 11.485, 6.735], "texture": "#2"},
				"south": {"uv": [13.265, 4.515, 13.485, 6.735], "texture": "#2"},
				"west": {"uv": [10.515, 6.765, 11.485, 8.985], "texture": "#2"},
				"up": {"uv": [14.485, 4.735, 14.265, 3.765], "texture": "#2"},
				"down": {"uv": [14.485, 4.765, 14.265, 5.735], "texture": "#2"}
			}
		},
		{
			"from": [7.5, 6.25, 5],
			"to": [8.5, 10.25, 5.5],
			"rotation": {"angle": 45, "axis": "x", "origin": [8, 8, 7.75]},
			"faces": {
				"north": {"uv": [11.515, 4.265, 11.985, 6.235], "texture": "#2"},
				"east": {"uv": [13.515, 0.015, 13.735, 1.985], "texture": "#2"},
				"south": {"uv": [4.515, 11.515, 4.985, 13.485], "texture": "#2"},
				"west": {"uv": [13.515, 2.015, 13.735, 3.985], "texture": "#2"},
				"up": {"uv": [14.985, 5.235, 14.515, 5.015], "texture": "#2"},
				"down": {"uv": [5.735, 14.515, 5.265, 14.735], "texture": "#2"}
			}
		},
		{
			"from": [7.5, 8.35355, 3.42157],
			"to": [8.5, 8.85355, 4.92157],
			"rotation": {"angle": 0, "axis": "y", "origin": [8, 6.60355, 7.17157]},
			"faces": {
				"north": {"uv": [14.515, 5.265, 14.985, 5.485], "texture": "#2"},
				"east": {"uv": [14.265, 12.265, 14.985, 12.485], "texture": "#2"},
				"south": {"uv": [14.515, 5.515, 14.985, 5.735], "texture": "#2"},
				"west": {"uv": [12.765, 14.265, 13.485, 14.485], "texture": "#2"},
				"up": {"uv": [2.485, 14.485, 2.015, 13.765], "texture": "#2"},
				"down": {"uv": [2.985, 13.765, 2.515, 14.485], "texture": "#2"}
			}
		},
		{
			"from": [7.5, 11.03553, 7.39645],
			"to": [8.5, 11.53553, 8.89645],
			"rotation": {"angle": 0, "axis": "y", "origin": [8, 11.28553, 8.14645]},
			"faces": {
				"north": {"uv": [5.765, 14.515, 6.235, 14.735], "texture": "#2"},
				"east": {"uv": [14.265, 13.515, 14.985, 13.735], "texture": "#2"},
				"south": {"uv": [14.515, 6.265, 14.985, 6.485], "texture": "#2"},
				"west": {"uv": [14.265, 13.765, 14.985, 13.985], "texture": "#2"},
				"up": {"uv": [14.235, 3.235, 13.765, 2.515], "texture": "#2"},
				"down": {"uv": [14.235, 3.265, 13.765, 3.985], "texture": "#2"}
			}
		},
		{
			"from": [7.5, 4.85355, 2.92157],
			"to": [8.5, 8.85355, 3.42157],
			"rotation": {"angle": 0, "axis": "y", "origin": [8, 6.60355, 7.17157]},
			"faces": {
				"north": {"uv": [5.015, 11.515, 5.485, 13.485], "texture": "#2"},
				"east": {"uv": [3.015, 13.515, 3.235, 15.485], "texture": "#2"},
				"south": {"uv": [5.515, 11.515, 5.985, 13.485], "texture": "#2"},
				"west": {"uv": [3.265, 13.515, 3.485, 15.485], "texture": "#2"},
				"up": {"uv": [14.985, 6.735, 14.515, 6.515], "texture": "#2"},
				"down": {"uv": [14.985, 6.765, 14.515, 6.985], "texture": "#2"}
			}
		},
		{
			"from": [7.5, 10.375, 7],
			"to": [8.5, 10.875, 9.5],
			"rotation": {"angle": 45, "axis": "x", "origin": [8, 7.625, 7.75]},
			"faces": {
				"north": {"uv": [7.015, 14.515, 7.485, 14.735], "texture": "#2"},
				"east": {"uv": [14.015, 1.265, 15.235, 1.485], "texture": "#2"},
				"south": {"uv": [14.515, 7.015, 14.985, 7.235], "texture": "#2"},
				"west": {"uv": [14.015, 1.515, 15.235, 1.735], "texture": "#2"},
				"up": {"uv": [13.235, 2.485, 12.765, 1.265], "texture": "#2"},
				"down": {"uv": [13.235, 2.515, 12.765, 3.735], "texture": "#2"}
			}
		},
		{
			"from": [7.75, 5.43566, 9.53553],
			"to": [8.25, 9.93566, 13.03553],
			"rotation": {"angle": 0, "axis": "y", "origin": [8, 7.68566, 7.78553]},
			"faces": {
				"north": {"uv": [13.265, 6.765, 13.485, 8.985], "texture": "#2"},
				"east": {"uv": [7.015, 4.515, 8.735, 6.735], "texture": "#2"},
				"south": {"uv": [13.265, 9.015, 13.485, 11.235], "texture": "#2"},
				"west": {"uv": [7.015, 6.765, 8.735, 8.985], "texture": "#2"},
				"up": {"uv": [8.985, 15.235, 8.765, 13.515], "texture": "#2"},
				"down": {"uv": [9.235, 13.515, 9.015, 15.235], "texture": "#2"}
			}
		},
		{
			"from": [7.5, 5.18566, 10.78553],
			"to": [8.5, 8.68566, 11.28553],
			"rotation": {"angle": 0, "axis": "y", "origin": [8, 7.93566, 8.03553]},
			"faces": {
				"north": {"uv": [10.515, 11.515, 10.985, 13.235], "texture": "#2"},
				"east": {"uv": [9.265, 13.515, 9.485, 15.235], "texture": "#2"},
				"south": {"uv": [11.015, 11.515, 11.485, 13.235], "texture": "#2"},
				"west": {"uv": [13.515, 9.765, 13.735, 11.485], "texture": "#2"},
				"up": {"uv": [14.985, 7.485, 14.515, 7.265], "texture": "#2"},
				"down": {"uv": [7.985, 14.515, 7.515, 14.735], "texture": "#2"}
			}
		},
		{
			"from": [7.5, 5.18566, 11.28553],
			"to": [8.5, 5.68566, 13.28553],
			"rotation": {"angle": 0, "axis": "y", "origin": [8, 7.93566, 8.03553]},
			"faces": {
				"north": {"uv": [14.515, 7.515, 14.985, 7.735], "texture": "#2"},
				"east": {"uv": [14.265, 5.765, 15.235, 5.985], "texture": "#2"},
				"south": {"uv": [14.515, 7.765, 14.985, 7.985], "texture": "#2"},
				"west": {"uv": [14.265, 6.015, 15.235, 6.235], "texture": "#2"},
				"up": {"uv": [3.985, 14.485, 3.515, 13.515], "texture": "#2"},
				"down": {"uv": [4.485, 13.515, 4.015, 14.485], "texture": "#2"}
			}
		},
		{
			"from": [8, 2.10355, -0.82843],
			"to": [8, 11.10355, 2.67157],
			"rotation": {"angle": 0, "axis": "y", "origin": [8, 6.35355, 6.92157]},
			"faces": {
				"north": {"uv": [0.015, 0.015, 0.015, 4.485], "texture": "#2"},
				"east": {"uv": [1.765, 4.515, 3.485, 8.985], "texture": "#2"},
				"south": {"uv": [0.015, 0.015, 0.015, 4.485], "texture": "#2"},
				"west": {"uv": [3.515, 4.515, 5.235, 8.985], "texture": "#2"},
				"up": {"uv": [0.015, 1.735, 0.015, 0.015], "texture": "#2"},
				"down": {"uv": [0.015, 0.015, 0.015, 1.735], "texture": "#2"}
			}
		},
		{
			"from": [7.75, 8.60355, 0.67157],
			"to": [8.25, 11.10355, 6.67157],
			"rotation": {"angle": 0, "axis": "y", "origin": [8, 6.35355, 6.92157]},
			"faces": {
				"north": {"uv": [14.015, 10.015, 14.235, 11.235], "texture": "#2"},
				"east": {"uv": [0.015, 10.265, 2.985, 11.485], "texture": "#2"},
				"south": {"uv": [14.015, 11.265, 14.235, 12.485], "texture": "#2"},
				"west": {"uv": [3.015, 10.265, 5.985, 11.485], "texture": "#2"},
				"up": {"uv": [12.735, 2.985, 12.515, 0.015], "texture": "#2"},
				"down": {"uv": [12.735, 3.015, 12.515, 5.985], "texture": "#2"}
			}
		},
		{
			"from": [7.75, 4.10355, 0.67157],
			"to": [8.25, 8.60355, 2.67157],
			"rotation": {"angle": 0, "axis": "y", "origin": [8, 6.35355, 6.92157]},
			"faces": {
				"north": {"uv": [9.515, 13.265, 9.735, 15.485], "texture": "#2"},
				"east": {"uv": [0.015, 11.515, 0.985, 13.735], "texture": "#2"},
				"south": {"uv": [9.765, 13.265, 9.985, 15.485], "texture": "#2"},
				"west": {"uv": [11.515, 0.015, 12.485, 2.235], "texture": "#2"},
				"up": {"uv": [14.485, 7.235, 14.265, 6.265], "texture": "#2"},
				"down": {"uv": [14.485, 7.265, 14.265, 8.235], "texture": "#2"}
			}
		},
		{
			"from": [7.5, 6.25, 4.5],
			"to": [8.5, 10.25, 5],
			"rotation": {"angle": 45, "axis": "x", "origin": [8, 8, 7.25]},
			"faces": {
				"north": {"uv": [6.015, 11.515, 6.485, 13.485], "texture": "#2"},
				"east": {"uv": [13.515, 4.015, 13.735, 5.985], "texture": "#2"},
				"south": {"uv": [11.515, 6.265, 11.985, 8.235], "texture": "#2"},
				"west": {"uv": [4.515, 13.515, 4.735, 15.485], "texture": "#2"},
				"up": {"uv": [14.985, 8.235, 14.515, 8.015], "texture": "#2"},
				"down": {"uv": [14.985, 8.765, 14.515, 8.985], "texture": "#2"}
			}
		},
		{
			"from": [7.5, 8.35355, 2.92157],
			"to": [8.5, 8.85355, 4.42157],
			"rotation": {"angle": 0, "axis": "y", "origin": [8, 6.60355, 6.67157]},
			"faces": {
				"north": {"uv": [14.515, 9.015, 14.985, 9.235], "texture": "#2"},
				"east": {"uv": [14.265, 14.015, 14.985, 14.235], "texture": "#2"},
				"south": {"uv": [14.515, 9.265, 14.985, 9.485], "texture": "#2"},
				"west": {"uv": [14.265, 14.265, 14.985, 14.485], "texture": "#2"},
				"up": {"uv": [14.235, 4.735, 13.765, 4.015], "texture": "#2"},
				"down": {"uv": [14.235, 4.765, 13.765, 5.485], "texture": "#2"}
			}
		},
		{
			"from": [7.5, 11.03553, 6.89645],
			"to": [8.5, 11.53553, 8.39645],
			"rotation": {"angle": 0, "axis": "y", "origin": [8, 11.28553, 7.64645]},
			"faces": {
				"north": {"uv": [14.515, 9.515, 14.985, 9.735], "texture": "#2"},
				"east": {"uv": [14.515, 0.015, 15.235, 0.235], "texture": "#2"},
				"south": {"uv": [14.515, 9.765, 14.985, 9.985], "texture": "#2"},
				"west": {"uv": [14.515, 0.265, 15.235, 0.485], "texture": "#2"},
				"up": {"uv": [14.235, 6.235, 13.765, 5.515], "texture": "#2"},
				"down": {"uv": [14.235, 6.265, 13.765, 6.985], "texture": "#2"}
			}
		},
		{
			"from": [7.5, 4.85355, 2.42157],
			"to": [8.5, 8.85355, 2.92157],
			"rotation": {"angle": 0, "axis": "y", "origin": [8, 6.60355, 6.67157]},
			"faces": {
				"north": {"uv": [6.515, 11.515, 6.985, 13.485], "texture": "#2"},
				"east": {"uv": [4.765, 13.515, 4.985, 15.485], "texture": "#2"},
				"south": {"uv": [7.015, 11.515, 7.485, 13.485], "texture": "#2"},
				"west": {"uv": [5.015, 13.515, 5.235, 15.485], "texture": "#2"},
				"up": {"uv": [14.985, 10.235, 14.515, 10.015], "texture": "#2"},
				"down": {"uv": [14.985, 10.265, 14.515, 10.485], "texture": "#2"}
			}
		},
		{
			"from": [7.5, 10.375, 7.5],
			"to": [8.5, 10.875, 10],
			"rotation": {"angle": 45, "axis": "x", "origin": [8, 7.625, 8.25]},
			"faces": {
				"north": {"uv": [14.515, 10.515, 14.985, 10.735], "texture": "#2"},
				"east": {"uv": [14.015, 13.015, 15.235, 13.235], "texture": "#2"},
				"south": {"uv": [12.765, 14.515, 13.235, 14.735], "texture": "#2"},
				"west": {"uv": [14.015, 13.265, 15.235, 13.485], "texture": "#2"},
				"up": {"uv": [13.235, 4.985, 12.765, 3.765], "texture": "#2"},
				"down": {"uv": [13.235, 5.015, 12.765, 6.235], "texture": "#2"}
			}
		},
		{
			"from": [7.75, 5.43566, 10.03553],
			"to": [8.25, 9.93566, 13.53553],
			"rotation": {"angle": 0, "axis": "y", "origin": [8, 7.68566, 8.28553]},
			"faces": {
				"north": {"uv": [10.015, 13.265, 10.235, 15.485], "texture": "#2"},
				"east": {"uv": [8.765, 0.015, 10.485, 2.235], "texture": "#2"},
				"south": {"uv": [10.265, 13.265, 10.485, 15.485], "texture": "#2"},
				"west": {"uv": [8.765, 2.265, 10.485, 4.485], "texture": "#2"},
				"up": {"uv": [13.735, 13.235, 13.515, 11.515], "texture": "#2"},
				"down": {"uv": [12.235, 13.515, 12.015, 15.235], "texture": "#2"}
			}
		},
		{
			"from": [7.5, 5.18566, 11.28553],
			"to": [8.5, 8.68566, 11.78553],
			"rotation": {"angle": 0, "axis": "y", "origin": [8, 7.93566, 8.53553]},
			"faces": {
				"north": {"uv": [11.515, 11.515, 11.985, 13.235], "texture": "#2"},
				"east": {"uv": [12.265, 13.515, 12.485, 15.235], "texture": "#2"},
				"south": {"uv": [12.015, 2.265, 12.485, 3.985], "texture": "#2"},
				"west": {"uv": [0.015, 13.765, 0.235, 15.485], "texture": "#2"},
				"up": {"uv": [13.735, 14.735, 13.265, 14.515], "texture": "#2"},
				"down": {"uv": [14.735, 14.515, 14.265, 14.735], "texture": "#2"}
			}
		},
		{
			"from": [7.5, 5.18566, 11.78553],
			"to": [8.5, 5.68566, 13.78553],
			"rotation": {"angle": 0, "axis": "y", "origin": [8, 7.93566, 8.53553]},
			"faces": {
				"north": {"uv": [1.015, 14.765, 1.485, 14.985], "texture": "#2"},
				"east": {"uv": [14.265, 8.265, 15.235, 8.485], "texture": "#2"},
				"south": {"uv": [1.515, 14.765, 1.985, 14.985], "texture": "#2"},
				"west": {"uv": [14.265, 8.515, 15.235, 8.735], "texture": "#2"},
				"up": {"uv": [5.735, 14.485, 5.265, 13.515], "texture": "#2"},
				"down": {"uv": [6.235, 13.515, 5.765, 14.485], "texture": "#2"}
			}
		},
		{
			"from": [8, 2.10355, -1.32843],
			"to": [8, 11.10355, 2.17157],
			"rotation": {"angle": 0, "axis": "y", "origin": [8, 6.35355, 6.42157]},
			"faces": {
				"north": {"uv": [0.015, 0.015, 0.015, 4.485], "texture": "#2"},
				"east": {"uv": [5.265, 0.015, 6.985, 4.485], "texture": "#2"},
				"south": {"uv": [0.015, 0.015, 0.015, 4.485], "texture": "#2"},
				"west": {"uv": [5.265, 4.515, 6.985, 8.985], "texture": "#2"},
				"up": {"uv": [0.015, 1.735, 0.015, 0.015], "texture": "#2"},
				"down": {"uv": [0.015, 0.015, 0.015, 1.735], "texture": "#2"}
			}
		},
		{
			"from": [7.75, 8.60355, 0.17157],
			"to": [8.25, 11.10355, 6.17157],
			"rotation": {"angle": 0, "axis": "y", "origin": [8, 6.35355, 6.42157]},
			"faces": {
				"north": {"uv": [14.015, 13.515, 14.235, 14.735], "texture": "#2"},
				"east": {"uv": [6.015, 10.265, 8.985, 11.485], "texture": "#2"},
				"south": {"uv": [14.265, 0.015, 14.485, 1.235], "texture": "#2"},
				"west": {"uv": [9.015, 10.265, 11.985, 11.485], "texture": "#2"},
				"up": {"uv": [12.735, 8.985, 12.515, 6.015], "texture": "#2"},
				"down": {"uv": [12.735, 9.015, 12.515, 11.985], "texture": "#2"}
			}
		},
		{
			"from": [7.75, 4.10355, 0.17157],
			"to": [8.25, 8.60355, 2.17157],
			"rotation": {"angle": 0, "axis": "y", "origin": [8, 6.35355, 6.42157]},
			"faces": {
				"north": {"uv": [10.515, 13.265, 10.735, 15.485], "texture": "#2"},
				"east": {"uv": [1.015, 11.515, 1.985, 13.735], "texture": "#2"},
				"south": {"uv": [10.765, 13.265, 10.985, 15.485], "texture": "#2"},
				"west": {"uv": [2.015, 11.515, 2.985, 13.735], "texture": "#2"},
				"up": {"uv": [14.485, 9.735, 14.265, 8.765], "texture": "#2"},
				"down": {"uv": [14.485, 9.765, 14.265, 10.735], "texture": "#2"}
			}
		},
		{
			"from": [7.5, 6.25, 4],
			"to": [8.5, 10.25, 4.5],
			"rotation": {"angle": 45, "axis": "x", "origin": [8, 8, 6.75]},
			"faces": {
				"north": {"uv": [7.515, 11.515, 7.985, 13.485], "texture": "#2"},
				"east": {"uv": [13.515, 6.015, 13.735, 7.985], "texture": "#2"},
				"south": {"uv": [8.015, 11.515, 8.485, 13.485], "texture": "#2"},
				"west": {"uv": [6.265, 13.515, 6.485, 15.485], "texture": "#2"},
				"up": {"uv": [2.485, 14.985, 2.015, 14.765], "texture": "#2"},
				"down": {"uv": [2.985, 14.765, 2.515, 14.985], "texture": "#2"}
			}
		},
		{
			"from": [7.5, 8.35355, 2.42157],
			"to": [8.5, 8.85355, 3.92157],
			"rotation": {"angle": 0, "axis": "y", "origin": [8, 6.60355, 6.17157]},
			"faces": {
				"north": {"uv": [3.515, 14.765, 3.985, 14.985], "texture": "#2"},
				"east": {"uv": [14.515, 0.515, 15.235, 0.735], "texture": "#2"},
				"south": {"uv": [4.015, 14.765, 4.485, 14.985], "texture": "#2"},
				"west": {"uv": [14.515, 0.765, 15.235, 0.985], "texture": "#2"},
				"up": {"uv": [14.235, 7.735, 13.765, 7.015], "texture": "#2"},
				"down": {"uv": [14.235, 7.765, 13.765, 8.485], "texture": "#2"}
			}
		},
		{
			"from": [7.5, 11.03553, 6.39645],
			"to": [8.5, 11.53553, 7.89645],
			"rotation": {"angle": 0, "axis": "y", "origin": [8, 11.28553, 7.14645]},
			"faces": {
				"north": {"uv": [5.265, 14.765, 5.735, 14.985], "texture": "#2"},
				"east": {"uv": [1.015, 14.515, 1.735, 14.735], "texture": "#2"},
				"south": {"uv": [5.765, 14.765, 6.235, 14.985], "texture": "#2"},
				"west": {"uv": [14.515, 1.015, 15.235, 1.235], "texture": "#2"},
				"up": {"uv": [14.235, 9.235, 13.765, 8.515], "texture": "#2"},
				"down": {"uv": [14.235, 9.265, 13.765, 9.985], "texture": "#2"}
			}
		},
		{
			"from": [7.5, 4.85355, 1.92157],
			"to": [8.5, 8.85355, 2.42157],
			"rotation": {"angle": 0, "axis": "y", "origin": [8, 6.60355, 6.17157]},
			"faces": {
				"north": {"uv": [8.515, 11.515, 8.985, 13.485], "texture": "#2"},
				"east": {"uv": [6.515, 13.515, 6.735, 15.485], "texture": "#2"},
				"south": {"uv": [9.015, 11.515, 9.485, 13.485], "texture": "#2"},
				"west": {"uv": [6.765, 13.515, 6.985, 15.485], "texture": "#2"},
				"up": {"uv": [7.485, 14.985, 7.015, 14.765], "texture": "#2"},
				"down": {"uv": [7.985, 14.765, 7.515, 14.985], "texture": "#2"}
			}
		},
		{
			"from": [7.5, 10.375, 8],
			"to": [8.5, 10.875, 10.5],
			"rotation": {"angle": 45, "axis": "x", "origin": [8, 7.625, 8.75]},
			"faces": {
				"north": {"uv": [12.765, 14.765, 13.235, 14.985], "texture": "#2"},
				"east": {"uv": [14.265, 1.765, 15.485, 1.985], "texture": "#2"},
				"south": {"uv": [13.265, 14.765, 13.735, 14.985], "texture": "#2"},
				"west": {"uv": [14.265, 2.015, 15.485, 2.235], "texture": "#2"},
				"up": {"uv": [13.235, 7.485, 12.765, 6.265], "texture": "#2"},
				"down": {"uv": [13.235, 7.515, 12.765, 8.735], "texture": "#2"}
			}
		},
		{
			"from": [7.75, 5.43566, 10.53553],
			"to": [8.25, 9.93566, 14.03553],
			"rotation": {"angle": 0, "axis": "y", "origin": [8, 7.68566, 8.78553]},
			"faces": {
				"north": {"uv": [11.015, 13.265, 11.235, 15.485], "texture": "#2"},
				"east": {"uv": [8.765, 4.515, 10.485, 6.735], "texture": "#2"},
				"south": {"uv": [11.265, 13.265, 11.485, 15.485], "texture": "#2"},
				"west": {"uv": [8.765, 6.765, 10.485, 8.985], "texture": "#2"},
				"up": {"uv": [13.985, 1.735, 13.765, 0.015], "texture": "#2"},
				"down": {"uv": [0.485, 13.765, 0.265, 15.485], "texture": "#2"}
			}
		},
		{
			"from": [7.5, 5.18566, 11.78553],
			"to": [8.5, 8.68566, 12.28553],
			"rotation": {"angle": 0, "axis": "y", "origin": [8, 7.93566, 9.03553]},
			"faces": {
				"north": {"uv": [12.015, 4.015, 12.485, 5.735], "texture": "#2"},
				"east": {"uv": [0.515, 13.765, 0.735, 15.485], "texture": "#2"},
				"south": {"uv": [12.015, 5.765, 12.485, 7.485], "texture": "#2"},
				"west": {"uv": [0.765, 13.765, 0.985, 15.485], "texture": "#2"},
				"up": {"uv": [14.235, 14.985, 13.765, 14.765], "texture": "#2"},
				"down": {"uv": [14.735, 14.765, 14.265, 14.985], "texture": "#2"}
			}
		},
		{
			"from": [7.5, 5.18566, 12.28553],
			"to": [8.5, 5.68566, 14.28553],
			"rotation": {"angle": 0, "axis": "y", "origin": [8, 7.93566, 9.03553]},
			"faces": {
				"north": {"uv": [14.765, 14.515, 15.235, 14.735], "texture": "#2"},
				"east": {"uv": [14.265, 10.765, 15.235, 10.985], "texture": "#2"},
				"south": {"uv": [14.765, 14.765, 15.235, 14.985], "texture": "#2"},
				"west": {"uv": [14.265, 11.015, 15.235, 11.235], "texture": "#2"},
				"up": {"uv": [7.485, 14.485, 7.015, 13.515], "texture": "#2"},
				"down": {"uv": [7.985, 13.515, 7.515, 14.485], "texture": "#2"}
			}
		}
	],
	"gui_light": "front",
	"display": {
		"thirdperson_righthand": {
			"translation": [0, 10.5, 1.5]
		},
		"thirdperson_lefthand": {
			"translation": [0, 10.75, 1.5]
		},
		"firstperson_righthand": {
			"rotation": [-12, 7, 0],
			"translation": [4.25, 8.5, -5.25]
		},
		"firstperson_lefthand": {
			"rotation": [-12, 7, 0],
			"translation": [4.25, 8.5, -5.25]
		},
		"ground": {
			"rotation": [-45, 0, 0],
			"translation": [0, 13.5, -5]
		},
		"gui": {
			"rotation": [-90, 135, 90],
			"translation": [2, 1.5, 0],
			"scale": [0.7, 0.7, 0.7]
		},
		"fixed": {
			"rotation": [90, -45, 90],
			"translation": [-2.5, 1.75, -0.5],
			"scale": [0.85, 0.85, 0.85]
		}
	},
	"groups": [
		{
			"name": "group",
			"origin": [8, 8.20711, 7.62817],
			"color": 0,
			"children": [0, 1, 2, 3, 4, 5, 6, 7, 8, 9]
		},
		10,
		{
			"name": "0",
			"origin": [8, 8, 8],
			"color": 0,
			"children": [
				{
					"name": "blade",
					"origin": [8, 13.20711, 6.34315],
					"color": 0,
					"children": [11, 12, 13, 14, 15, 16, 17]
				},
				{
					"name": "back",
					"origin": [8, 16.62132, 9.07107],
					"color": 0,
					"children": [18, 19, 20, 21]
				}
			]
		},
		{
			"name": "1",
			"origin": [8, 8, 8],
			"color": 0,
			"children": [
				{
					"name": "blade",
					"origin": [8, 13.20711, 6.34315],
					"color": 0,
					"children": [22, 23, 24, 25, 26, 27, 28]
				},
				{
					"name": "back",
					"origin": [8, 16.62132, 9.07107],
					"color": 0,
					"children": [29, 30, 31, 32]
				}
			]
		},
		{
			"name": "2",
			"origin": [8, 8, 8],
			"color": 0,
			"children": [
				{
					"name": "blade",
					"origin": [8, 13.20711, 6.34315],
					"color": 0,
					"children": [33, 34, 35, 36, 37, 38, 39]
				},
				{
					"name": "back",
					"origin": [8, 16.62132, 9.07107],
					"color": 0,
					"children": [40, 41, 42, 43]
				}
			]
		},
		{
			"name": "3",
			"origin": [8, 8, 8],
			"color": 0,
			"children": [
				{
					"name": "blade",
					"origin": [8, 13.20711, 6.34315],
					"color": 0,
					"children": [44, 45, 46, 47, 48, 49, 50]
				},
				{
					"name": "back",
					"origin": [8, 16.62132, 9.07107],
					"color": 0,
					"children": [51, 52, 53, 54]
				}
			]
		}
	]
}